helen_electricity_usage/__init__.py
helen_electricity_usage-0.5.0.dist-info/LICENSE.txt
helen_electricity_usage-0.5.0.dist-info/METADATA
helen_electricity_usage-0.5.0.dist-info/WHEEL
helen_electricity_usage-0.5.0.dist-info/top_level.txt
helen_electricity_usage-0.5.0.dist-info/RECORD
