Metadata-Version: 2.1
Name: helen-electricity-usage
Version: 0.5.0
Summary: Small library for scraping electricity usage information from Helsingin Energia website
Home-page: https://github.com/ojarva/python-helen-electricity-usage
Author: Olli Jarva
Author-email: olli@jarva.fi
License: BSD
Keywords: electricity helen
Platform: UNKNOWN
Classifier: Development Status :: 4 - Beta
Classifier: Intended Audience :: Developers
Classifier: Topic :: Internet
Classifier: License :: OSI Approved :: BSD License
Classifier: Programming Language :: Python :: 2.7
Classifier: Programming Language :: Python :: 3
Classifier: Programming Language :: Python :: 3.3
Classifier: Programming Language :: Python :: 3.4
Classifier: Programming Language :: Python :: 3.5
Classifier: Programming Language :: Python :: Implementation :: PyPy
Requires-Dist: requests (>=2.5.1)
Requires-Dist: beautifulsoup4 (>=4.4.1)
Provides-Extra: dev
Requires-Dist: twine ; extra == 'dev'
Requires-Dist: wheel ; extra == 'dev'
